aztime_sozle/__init__.py
aztime_sozle-0.1.1.dist-info/licenses/LICENSE
aztime_sozle-0.1.1.dist-info/METADATA
aztime_sozle-0.1.1.dist-info/WHEEL
aztime_sozle-0.1.1.dist-info/top_level.txt
aztime_sozle-0.1.1.dist-info/RECORD
