Metadata-Version: 2.4
Name: aztime_sozle
Version: 0.1.1
Summary: Azərbaycan dilində HH:MM formatındakı saatı sözlərlə ifadə edən kitabxana.
Home-page: https://github.com/Eldar/aztime_sozle
Author: Eldar
Author-email: emailiniz@example.com
Classifier: Programming Language :: Python :: 3
Classifier: License :: OSI Approved :: MIT License
Classifier: Operating System :: OS Independent
Classifier: Development Status :: 4 - Beta
Classifier: Topic :: Utilities
Requires-Python: >=3.6
License-File: LICENSE
Dynamic: author
Dynamic: author-email
Dynamic: classifier
Dynamic: description
Dynamic: description-content-type
Dynamic: home-page
Dynamic: license-file
Dynamic: requires-python
Dynamic: summary
